Metadata-Version: 1.0
Name: vep-distributions
Version: 1.0
Summary: Gaussian and Binomial distributions
Home-page: UNKNOWN
Author: Joshua Olaku
Author-email: joshuaolaku@gmail.com
License: UNKNOWN
Platform: UNKNOWN
